dirs_and_dict/__init__.py
dirs_and_dict/dirs_dict.py
dirs_and_dict/modules/__init__.py
dirs_and_dict-1.0.0.dist-info/LICENSE
dirs_and_dict-1.0.0.dist-info/METADATA
dirs_and_dict-1.0.0.dist-info/WHEEL
dirs_and_dict-1.0.0.dist-info/top_level.txt
dirs_and_dict-1.0.0.dist-info/RECORD
