Metadata-Version: 2.1
Name: dirs-and-dict
Version: 1.0.0
Summary: A lightweight solution to creating folder structures from dicts, in Python
Home-page: https://github.com/Whoeza/dirs_and_dict
Author: Whoeza
License: GNU GPLv3
Project-URL: Bug Tracker, https://github.com/Whoeza/dirs_and_dict/issues
Classifier: Intended Audience :: Developers
Classifier: License :: OSI Approved :: GNU General Public License v3 (GPLv3)
Classifier: Operating System :: OS Independent
Classifier: Programming Language :: Python :: 3
Requires-Python: >=3.10
License-File: LICENSE
